kiwixstorage/__about__.py
kiwixstorage/__init__.py
kiwixstorage/test_credentials.py
kiwixstorage/upload.py
kiwixstorage-0.10.1.dist-info/METADATA
kiwixstorage-0.10.1.dist-info/WHEEL
kiwixstorage-0.10.1.dist-info/entry_points.txt
kiwixstorage-0.10.1.dist-info/licenses/LICENSE
kiwixstorage-0.10.1.dist-info/RECORD
